chronos/__init__.py
chronos/copy_correction.py
chronos/evaluations.py
chronos/fetch_parameters.py
chronos/figshare.py
chronos/model.py
chronos/plotting.py
chronos/reports.py
crispr_chronos-2.0.6.dist-info/LICENSE
crispr_chronos-2.0.6.dist-info/METADATA
crispr_chronos-2.0.6.dist-info/WHEEL
crispr_chronos-2.0.6.dist-info/top_level.txt
crispr_chronos-2.0.6.dist-info/RECORD
