Metadata-Version: 2.1
Name: crispr-chronos
Version: 2.0.6
Summary: Time series modeling of CRISPR perturbation readcounts in biological data
Author: BroadInstitute CDS
License-File: LICENSE
Requires-Dist: adjustText
Requires-Dist: h5py (>=3.7)
Requires-Dist: matplotlib (>=3.6)
Requires-Dist: numpy (>=1.2)
Requires-Dist: pandas (>=1.3)
Requires-Dist: patsy (>=0.5.2)
Requires-Dist: reportlab (>=3.6)
Requires-Dist: scikit-learn (>=1.1)
Requires-Dist: scipy (>=1.9)
Requires-Dist: seaborn (>=0.12)
Requires-Dist: statsmodels (>=0.13)
Requires-Dist: tensorflow (>2)
Requires-Dist: umap-learn (>=0.5.3)
